{"120245539486000384": {"name": "ntn_wanda_loose_jewellery_velore_chain_reel_clp_200626", "roas": 0.35, "roas_yday": null, "roas_7d": 0.35, "budget": 35000.0, "camp_type": "TOF", "bucket_label": "\ud83c\udd95 Day 0", "run_label": "21 Jun 02:15 PM IST"}, "120245539318310384": {"name": "ntn_wanda_sales_conv_jewellery_packof2_multiple_reel_clp_200626 \u2013 Copy", "roas": 1.42, "roas_yday": null, "roas_7d": 1.42, "budget": 15000.0, "camp_type": "Retarget", "bucket_label": "\ud83c\udd95 Day 0", "run_label": "21 Jun 02:15 PM IST"}, "120245538997740384": {"name": "ntn_wanda_sales_jewellery_velore_chain_reel_clp_200626", "roas": 0.55, "roas_yday": null, "roas_7d": 0.55, "budget": 40000.0, "camp_type": "Retarget", "bucket_label": "\ud83c\udd95 Day 0", "run_label": "21 Jun 02:15 PM IST"}, "120245538749730384": {"name": "ntn_wanda_loose_jewellery_velore_chain_reel_clp_200626", "roas": 0.66, "roas_yday": null, "roas_7d": 0.66, "budget": 35000.0, "camp_type": "TOF", "bucket_label": "\ud83c\udd95 Day 0", "run_label": "21 Jun 02:15 PM IST"}, "120245538529180384": {"name": "ntn_loose_wanda_new_pendant_jewellery_reel_clp_200626", "roas": 0.38, "roas_yday": null, "roas_7d": 0.38, "budget": 5000.0, "camp_type": "TOF", "bucket_label": "\ud83c\udd95 Day 0", "run_label": "21 Jun 02:15 PM IST"}, "120245481582740384": {"name": "ntn_wanda_loose_jewellery_pendant_chain_reel_clp_200626", "roas": 2.84, "roas_yday": 1.47, "roas_7d": 2.08, "budget": 2000.0, "camp_type": "TOF", "bucket_label": "\ud83d\udcc5 Day 1", "run_label": "21 Jun 02:15 PM IST"}, "120245481198670384": {"name": "ntn_wanda_loose_jewellery_pendant_chain_reel_clp_200626", "roas": 1.2, "roas_yday": 0.41, "roas_7d": 0.71, "budget": 1000.0, "camp_type": "TOF", "bucket_label": "\ud83d\udcc5 Day 1", "run_label": "21 Jun 02:15 PM IST"}, "120245479712950384": {"name": "ntn_wanda_sales_conv_jewellery_multiple_pendant_buy3@799_2_pendents_1_velore_chain_reel_clp_200626", "roas": 2.29, "roas_yday": 0.34, "roas_7d": 1.0, "budget": 1250.0, "camp_type": "Retarget", "bucket_label": "\ud83d\udcc5 Day 1", "run_label": "21 Jun 02:15 PM IST"}, "120245478747120384": {"name": "ntn_adv_web_conv_paras_partnership_Chain_2_reel_200626", "roas": 0.96, "roas_yday": 1.87, "roas_7d": 1.54, "budget": 10000.0, "camp_type": "Retarget", "bucket_label": "\ud83d\udcc5 Day 1", "run_label": "21 Jun 02:15 PM IST"}, "120245478492820384": {"name": "ntn_adv_web_conv_rtg_paras_partnership_Chain_reel_200626 \u2013 Copy", "roas": 1.41, "roas_yday": 2.94, "roas_7d": 2.41, "budget": 2500.0, "camp_type": "Retarget", "bucket_label": "\ud83d\udcc5 Day 1", "run_label": "21 Jun 02:15 PM IST"}, "120245478064570384": {"name": "ntn_wanda_sales_conv_jewellery_multiple_pendant_buy3@799_2_pendents_1_velore_chain_reel_clp_200626", "roas": 0.96, "roas_yday": 2.42, "roas_7d": 1.94, "budget": 5000.0, "camp_type": "Retarget", "bucket_label": "\ud83d\udcc5 Day 1", "run_label": "21 Jun 02:15 PM IST"}, "120245477779520384": {"name": "ntn_adv_web_conv_paras_partnership_Chain_reel_200626", "roas": 1.47, "roas_yday": 2.58, "roas_7d": 2.19, "budget": 10000.0, "camp_type": "Retarget", "bucket_label": "\ud83d\udcc5 Day 1", "run_label": "21 Jun 02:15 PM IST"}, "120245476394910384": {"name": "ntn_wanda_retarget_conv_jewellery_multiple_packof2_reel_clp_200626", "roas": 1.61, "roas_yday": 0.97, "roas_7d": 1.16, "budget": 5000.0, "camp_type": "Retarget", "bucket_label": "\ud83d\udcc5 Day 1", "run_label": "21 Jun 02:15 PM IST"}, "120245475714070384": {"name": "ntn_wanda_sales_conv_jewellery_packof2_multiple_reel_clp_200626", "roas": 1.55, "roas_yday": 1.71, "roas_7d": 1.65, "budget": 10000.0, "camp_type": "Retarget", "bucket_label": "\ud83d\udcc5 Day 1", "run_label": "21 Jun 02:15 PM IST"}, "120245475389130384": {"name": "ntn_wanda_sales_conv_jewellery_packof2_velore_chain_reel_clp_200626", "roas": 0.15, "roas_yday": 0.37, "roas_7d": 0.27, "budget": 3750.0, "camp_type": "Retarget", "bucket_label": "\ud83d\udcc5 Day 1", "run_label": "21 Jun 02:15 PM IST"}, "120245475196810384": {"name": "ntn_wanda_loose_conv_jewellery_packof2_velore_chain_reel_clp_200626", "roas": 0.75, "roas_yday": 0.64, "roas_7d": 0.68, "budget": 5000.0, "camp_type": "TOF", "bucket_label": "\ud83d\udcc5 Day 1", "run_label": "21 Jun 02:15 PM IST"}, "120245473941280384": {"name": "ntn_wanda_sales_conv_jewellery_packof2_velore_chain_reel_clp_200626", "roas": 1.17, "roas_yday": null, "roas_7d": 0.54, "budget": 3750.0, "camp_type": "Retarget", "bucket_label": "\ud83d\udcc5 Day 1", "run_label": "21 Jun 02:15 PM IST"}, "120245460696500384": {"name": "ntn_wanda_sales_jewellery_offer_rice_velore_chain_packof2_reel_clp_190626 \u2013 Copy 6", "roas": 1.99, "roas_yday": null, "roas_7d": 0.85, "budget": 1250.0, "camp_type": "Retarget", "bucket_label": "\ud83d\udcc5 Day 2", "run_label": "21 Jun 02:15 PM IST"}, "120245459681200384": {"name": "ntn_wanda_rtg_jewellery_offer_rice_chain_packof2_reel_clp_190626 \u2013 Copy 5", "roas": 0.86, "roas_yday": 0.26, "roas_7d": 0.42, "budget": 2250.0, "camp_type": "Retarget", "bucket_label": "\ud83d\udcc5 Day 2", "run_label": "21 Jun 02:15 PM IST"}, "120245458713170384": {"name": "ntn_wanda_sale_jewellery_offer_packof2_paras_videos_reel_clp_190626", "roas": 1.58, "roas_yday": 1.88, "roas_7d": 1.78, "budget": 10000.0, "camp_type": "Retarget", "bucket_label": "\ud83d\udcc5 Day 2", "run_label": "21 Jun 02:15 PM IST"}, "120245452795940384": {"name": "ntn_wanda_rtg_jewellery_offer_packof2_reel_clp_190626 \u2013 Copy 4", "roas": 0.52, "roas_yday": 0.62, "roas_7d": 0.87, "budget": 2500.0, "camp_type": "Retarget", "bucket_label": "\ud83d\udcc5 Day 2", "run_label": "21 Jun 02:15 PM IST"}, "120245452681000384": {"name": "ntn_wanda_rtg_jewellery_offer_packof2_reel_clp_190626 \u2013 Copy 3", "roas": 1.18, "roas_yday": 1.71, "roas_7d": 1.81, "budget": 3500.0, "camp_type": "Retarget", "bucket_label": "\ud83d\udcc5 Day 2", "run_label": "21 Jun 02:15 PM IST"}, "120245423933100384": {"name": "ntn_wanda_sale_jewellery_offer_aesthetic_pyrite_locket_b1g1_reel_clp_190626 \u2013 Copy 6", "roas": 1.05, "roas_yday": 1.63, "roas_7d": 1.03, "budget": 1500.0, "camp_type": "Retarget", "bucket_label": "\ud83d\udcc5 Day 2", "run_label": "21 Jun 02:15 PM IST"}, "120245423924160384": {"name": "ntn_wanda_rtg_jewellery_offer_aesthetic_pyrite_locket_b1g1_reel_clp_190626 \u2013 Copy 7", "roas": 3.48, "roas_yday": null, "roas_7d": 1.97, "budget": 1250.0, "camp_type": "Retarget", "bucket_label": "\ud83d\udcc5 Day 2", "run_label": "21 Jun 02:15 PM IST"}, "120245423908730384": {"name": "ntn_wanda_rtg_jewellery_offer_aesthetic_pyrite_locket_b1g1_reel_clp_190626 \u2013 Copy 6", "roas": 1.02, "roas_yday": 0.47, "roas_7d": 0.77, "budget": 1250.0, "camp_type": "Retarget", "bucket_label": "\ud83d\udcc5 Day 2", "run_label": "21 Jun 02:15 PM IST"}, "120245423767570384": {"name": "ntn_wanda_sale_jewellery_offer_aesthetic_pyrite_locket_b1g1_reel_clp_190626 \u2013 Copy 5", "roas": 1.32, "roas_yday": 1.97, "roas_7d": 1.83, "budget": 10000.0, "camp_type": "Retarget", "bucket_label": "\ud83d\udcc5 Day 2", "run_label": "21 Jun 02:15 PM IST"}, "120245423649410384": {"name": "ntn_wanda_sale_jewellery_offer_2pendent+1chain_reel_clp_190626 \u2013 Copy 4", "roas": 9.56, "roas_yday": 0.89, "roas_7d": 1.41, "budget": 750.0, "camp_type": "Retarget", "bucket_label": "\ud83d\udcc5 Day 2", "run_label": "21 Jun 02:15 PM IST"}, "120245423622470384": {"name": "ntn_wanda_rtg_jewellery_offer_2pendent+1chain_reel_clp_190626 \u2013 Copy 5", "roas": 4.58, "roas_yday": 4.46, "roas_7d": 3.36, "budget": 2500.0, "camp_type": "Retarget", "bucket_label": "\ud83d\udcc5 Day 2", "run_label": "21 Jun 02:15 PM IST"}, "120245423606260384": {"name": "ntn_wanda_rtg_jewellery_offer_2pendent+1chain_reel_clp_190626 \u2013 Copy 4", "roas": 0.59, "roas_yday": 2.28, "roas_7d": 2.1, "budget": 5000.0, "camp_type": "Retarget", "bucket_label": "\ud83d\udcc5 Day 2", "run_label": "21 Jun 02:15 PM IST"}, "120245423499930384": {"name": "ntn_wanda_sale_jewellery_offer_2pendent+1chain_reel_clp_190626 \u2013 Copy 3", "roas": 2.12, "roas_yday": 1.81, "roas_7d": 1.83, "budget": 9000.0, "camp_type": "Retarget", "bucket_label": "\ud83d\udcc5 Day 2", "run_label": "21 Jun 02:15 PM IST"}, "120245423442130384": {"name": "ntn_adv_web_rtg_jewellery_camp_reel_190626", "roas": 0.84, "roas_yday": 1.81, "roas_7d": 1.44, "budget": 2500.0, "camp_type": "Retarget", "bucket_label": "\ud83d\udcc5 Day 2", "run_label": "21 Jun 02:15 PM IST"}, "120245423363730384": {"name": "ntn_adv_web_rtg_jewellery_camp_reel_190626 \u2013 Copy 2", "roas": 1.87, "roas_yday": 2.02, "roas_7d": 1.85, "budget": 2500.0, "camp_type": "Retarget", "bucket_label": "\ud83d\udcc5 Day 2", "run_label": "21 Jun 02:15 PM IST"}, "120245423326270384": {"name": "ntn_adv_web_sales_jewellery_camp_reel_190626 \u2013 Copy", "roas": 1.15, "roas_yday": 0.55, "roas_7d": 0.65, "budget": 2500.0, "camp_type": "Retarget", "bucket_label": "\ud83d\udcc5 Day 2", "run_label": "21 Jun 02:15 PM IST"}, "120245422639000384": {"name": "ntn_wanda_rtg_jewellery_offer_packof2_reel_clp_190626 \u2013 Copy 2", "roas": 0.66, "roas_yday": 3.86, "roas_7d": 2.67, "budget": 2500.0, "camp_type": "Retarget", "bucket_label": "\ud83d\udcc5 Day 2", "run_label": "21 Jun 02:15 PM IST"}, "120245422599490384": {"name": "ntn_wanda_sale_jewellery_offer_packof2_reel_clp_190626 \u2013 Copy 2", "roas": 0.94, "roas_yday": 1.33, "roas_7d": 1.07, "budget": 1250.0, "camp_type": "Retarget", "bucket_label": "\ud83d\udcc5 Day 2", "run_label": "21 Jun 02:15 PM IST"}, "120245422590270384": {"name": "ntn_wanda_rtg_jewellery_offer_packof2_reel_clp_190626 \u2013 Copy", "roas": 0.69, "roas_yday": 2.88, "roas_7d": 2.19, "budget": 5000.0, "camp_type": "Retarget", "bucket_label": "\ud83d\udcc5 Day 2", "run_label": "21 Jun 02:15 PM IST"}, "120245422510350384": {"name": "ntn_wanda_loose_jewellery_offer_packof2_reel_clp_190626", "roas": 1.1, "roas_yday": 1.23, "roas_7d": 1.33, "budget": 20000.0, "camp_type": "TOF", "bucket_label": "\ud83d\udcc5 Day 2", "run_label": "21 Jun 02:15 PM IST"}, "120245420565290384": {"name": "ntn_adv_wanda_sales_jewellery_reel_clp_190626", "roas": 1.22, "roas_yday": 0.77, "roas_7d": 0.77, "budget": 10000.0, "camp_type": "Retarget", "bucket_label": "\ud83d\udcc5 Day 2", "run_label": "21 Jun 02:15 PM IST"}, "120245420395390384": {"name": "ntn_wanda_sales_conv_jewellery_reel_clp_190626", "roas": 1.21, "roas_yday": 0.68, "roas_7d": 0.78, "budget": 10000.0, "camp_type": "Retarget", "bucket_label": "\ud83d\udcc5 Day 2", "run_label": "21 Jun 02:15 PM IST"}, "120245335249090384": {"name": "ntn_wanda_loose_conv_jewellery_aesthetic_pyrite_locket_reel_clp_180626", "roas": 0.2, "roas_yday": 0.66, "roas_7d": 0.44, "budget": 6000.0, "camp_type": "TOF", "bucket_label": "\ud83d\udcc5 Day 3", "run_label": "21 Jun 02:15 PM IST"}, "120245300453680384": {"name": "ntn_adv_web_retarget_jewellery_chain_offer_camp_reel_170626 - Copy", "roas": 1.82, "roas_yday": 2.52, "roas_7d": 2.06, "budget": 7500.0, "camp_type": "Retarget", "bucket_label": "\ud83d\udcc6 Day 4\u20137", "run_label": "21 Jun 02:15 PM IST"}, "120245276834790384": {"name": "ntn_adv_web_sales_jewellery_chain_offer_camp_3_reel_170626 \u2013 Copy 2", "roas": 1.47, "roas_yday": 1.86, "roas_7d": 2.51, "budget": 15000.0, "camp_type": "Retarget", "bucket_label": "\ud83d\udcc6 Day 4\u20137", "run_label": "21 Jun 02:15 PM IST"}, "120245134250760384": {"name": "ntn_adv_web_sales_jewellery_chain_camp_reel_150626", "roas": 1.92, "roas_yday": 1.1, "roas_7d": 1.23, "budget": 3000.0, "camp_type": "Retarget", "bucket_label": "\ud83d\udcc6 Day 4\u20137", "run_label": "21 Jun 02:15 PM IST"}, "120244890362860384": {"name": "ntn_web_sales_partnership_jewellery_reel_3_clp_110626", "roas": 1.32, "roas_yday": 1.19, "roas_7d": 1.61, "budget": 3000.0, "camp_type": "Retarget", "bucket_label": "\u23f3 Day 7+ (10d)", "run_label": "21 Jun 02:15 PM IST"}, "120243916672480384": {"name": "bau_adv_web_conv_ampm_combo_reel_A/B_020626 - 230626", "roas": 0.0, "roas_yday": 1.37, "roas_7d": 1.59, "budget": 0.0, "camp_type": "Sales", "bucket_label": "\u23f3 Day 7+ (19d)", "run_label": "21 Jun 02:15 PM IST"}, "120243916669870384": {"name": "meta_test_adv_web_conv_ampm_combo_reel_A/B_020626 \u2013 230626", "roas": 0.0, "roas_yday": 0.97, "roas_7d": 1.16, "budget": 0.0, "camp_type": "Sales", "bucket_label": "\u23f3 Day 7+ (19d)", "run_label": "21 Jun 02:15 PM IST"}, "120243916470020384": {"name": "bau_wanda_sales_hair_phus_phus_night_combo_reel_clp_A/B_020626 - 230626", "roas": 0.64, "roas_yday": 0.25, "roas_7d": 0.21, "budget": 0.0, "camp_type": "Sales", "bucket_label": "\u23f3 Day 7+ (19d)", "run_label": "21 Jun 02:15 PM IST"}, "120243916457830384": {"name": "meta_test_wanda_sales_hair_phus_phus_night_combo_reel_clp_A/B_020626 -230626", "roas": 0.0, "roas_yday": 0.06, "roas_7d": 0.35, "budget": 0.0, "camp_type": "Sales", "bucket_label": "\u23f3 Day 7+ (19d)", "run_label": "21 Jun 02:15 PM IST"}, "120243916218850384": {"name": "meta_test_wanda_sales_partnership_peacock_frame_reel_clp_A/B_020626 -230626", "roas": 0.0, "roas_yday": null, "roas_7d": 0.07, "budget": 0.0, "camp_type": "Sales", "bucket_label": "\u23f3 Day 7+ (19d)", "run_label": "21 Jun 02:15 PM IST"}, "120243916121590384": {"name": "bau_wanda_sales_peacock_frame_reel_clp_A/B_020626-240626", "roas": 0.58, "roas_yday": 0.23, "roas_7d": 0.25, "budget": 0.0, "camp_type": "Sales", "bucket_label": "\u23f3 Day 7+ (19d)", "run_label": "21 Jun 02:15 PM IST"}, "120241131052770384": {"name": "ntn_adv_web_conv_rtg_selenite_coaster_reel_310326_n \u2013 Copy 5", "roas": 3.26, "roas_yday": 0.11, "roas_7d": 2.39, "budget": 7000.0, "camp_type": "Retarget", "bucket_label": "\u23f3 Day 7+ (82d)", "run_label": "21 Jun 02:15 PM IST"}, "120246560442880413": {"name": "LEADS | COLD | CreatorHunt | Ludhiana | Jun26", "roas": 0.0, "roas_yday": null, "roas_7d": 0.03, "budget": 5000.0, "camp_type": "TOF", "bucket_label": "\ud83d\udcc6 Day 4\u20137", "run_label": "21 Jun 02:15 PM IST"}, "120251854909110581": {"name": "ntn_adv_wanda_conv_peacock_frame_creatives_180626", "roas": 2.19, "roas_yday": 2.21, "roas_7d": 2.2, "budget": 5000.0, "camp_type": "Retarget", "bucket_label": "\ud83d\udcc5 Day 3", "run_label": "21 Jun 02:15 PM IST"}, "120251711985920581": {"name": "ntn_adv_web_conv_crystal_ganesha_reel_160626", "roas": 3.19, "roas_yday": 5.24, "roas_7d": 3.05, "budget": 2500.0, "camp_type": "Retarget", "bucket_label": "\ud83d\udcc6 Day 4\u20137", "run_label": "21 Jun 02:15 PM IST"}, "120251479173570581": {"name": "DUP_brand_frame_raiseandshine_partnersh_CBO3k", "roas": 1.65, "roas_yday": 1.92, "roas_7d": 2.38, "budget": 1500.0, "camp_type": "Sales", "bucket_label": "\u23f3 Day 7+ (9d)", "run_label": "21 Jun 02:15 PM IST"}, "120250704525680581": {"name": "ntn_adv_wanda_web_conv_richierich_bracelet_reel_clp_020626_offer (SC)", "roas": 1.93, "roas_yday": 1.62, "roas_7d": 1.76, "budget": 20000.0, "camp_type": "Retarget", "bucket_label": "\u23f3 Day 7+ (19d)", "run_label": "21 Jun 02:15 PM IST"}}